mcp_server_site_search/__init__.py
mcp_server_site_search/__main__.py
mcp_server_site_search/site_search.py
mcp_server_site_search-0.1.6.dist-info/METADATA
mcp_server_site_search-0.1.6.dist-info/WHEEL
mcp_server_site_search-0.1.6.dist-info/entry_points.txt
mcp_server_site_search-0.1.6.dist-info/licenses/LICENSE
mcp_server_site_search-0.1.6.dist-info/RECORD
