Metadata-Version: 2.4
Name: mcp-server-site-search
Version: 0.1.6
Summary: CUHKSZ Site Search MCP
Author-email: Ming Wen <wen123090613@gmail.com>
License-File: LICENSE
Keywords: CUHKSZ,MCP,Site Search
Classifier: License :: OSI Approved :: MIT License
Classifier: Operating System :: OS Independent
Classifier: Programming Language :: Python :: 3
Requires-Python: >=3.11
Requires-Dist: httpx>=0.28.1
Requires-Dist: mcp[cli]>=1.7.1
Requires-Dist: pydantic>=2.7.0
